fix_ligatures.py
fix_ligatures-0.1.0.dist-info/LICENSE
fix_ligatures-0.1.0.dist-info/METADATA
fix_ligatures-0.1.0.dist-info/WHEEL
fix_ligatures-0.1.0.dist-info/entry_points.txt
fix_ligatures-0.1.0.dist-info/top_level.txt
fix_ligatures-0.1.0.dist-info/RECORD
