Metadata-Version: 2.1
Name: fix-ligatures
Version: 0.1.0
Summary: A pre-commit fixer for replacing ligature characters.
Home-page: https://github.com/sirosen/fix-ligatures
Author: Stephen Rosen
Author-email: sirosen@uchicago.edu
License: UNKNOWN
Platform: UNKNOWN
Classifier: Development Status :: 3 - Alpha
Classifier: Intended Audience :: Developers
Classifier: License :: OSI Approved :: Apache Software License
Classifier: Programming Language :: Python :: 3
Requires-Python: >=3.6.2
Requires-Dist: identify (<2.0)
